<?xml version="1.0" encoding="Windows-1252"?>
<ObjectCollection xmlns:xsi="http://www.w3.org/2001/XMLSchema-instance" xmlns:xsd="http://www.w3.org/2001/XMLSchema">
  <O>
    <SceneObject>
      <name>barrel_group (2)</name>
      <path>Prefabs/prefab_props/barrel_group</path>
      <position>
        <x>151.1</x>
        <y>-3.82</y>
        <z>147.74</z>
      </position>
      <rotation>
        <x>270</x>
        <y>20.00004</y>
        <z>0</z>
      </rotation>
      <scale>
        <x>1.291333</x>
        <y>1.29133368</y>
        <z>1.04282773</z>
      </scale>
      <tilePosition>
        <x>150</x>
        <y>10</y>
        <z>130</z>
      </tilePosition>
      <coordinate>
        <x>5</x>
        <y>6</y>
      </coordinate>
      <type>building</type>
    </SceneObject>
    <SceneObject>
      <name>barrel (1)</name>
      <path>Prefabs/prefab_props/barrel</path>
      <position>
        <x>152.21</x>
        <y>-3.815</y>
        <z>153.63</z>
      </position>
      <rotation>
        <x>270</x>
        <y>20.0000515</y>
        <z>0</z>
      </rotation>
      <scale>
        <x>1.2599988</x>
        <y>1.25999892</y>
        <z>1.07760453</z>
      </scale>
      <tilePosition>
        <x>150</x>
        <y>10</y>
        <z>130</z>
      </tilePosition>
      <coordinate>
        <x>5</x>
        <y>6</y>
      </coordinate>
      <type>building</type>
    </SceneObject>
    <SceneObject>
      <name>barrel (2)</name>
      <path>Prefabs/prefab_props/barrel</path>
      <position>
        <x>156.71</x>
        <y>-3.09</y>
        <z>152.17</z>
      </position>
      <rotation>
        <x>4.26886836E-05</x>
        <y>336.728</y>
        <z>90.0000458</z>
      </rotation>
      <scale>
        <x>1.25999856</x>
        <y>1.2599988</y>
        <z>1.07760382</z>
      </scale>
      <tilePosition>
        <x>150</x>
        <y>10</y>
        <z>130</z>
      </tilePosition>
      <coordinate>
        <x>5</x>
        <y>6</y>
      </coordinate>
      <type>building</type>
    </SceneObject>
    <SceneObject>
      <name>box (1)</name>
      <path>Prefabs/prefab_props/box</path>
      <position>
        <x>160.31</x>
        <y>-3.81</y>
        <z>190.23</z>
      </position>
      <rotation>
        <x>270</x>
        <y>0</y>
        <z>0</z>
      </rotation>
      <scale>
        <x>1.95430791</x>
        <y>1.954309</y>
        <z>1.954309</z>
      </scale>
      <tilePosition>
        <x>150</x>
        <y>10</y>
        <z>130</z>
      </tilePosition>
      <coordinate>
        <x>5</x>
        <y>6</y>
      </coordinate>
      <type>building</type>
    </SceneObject>
    <SceneObject>
      <name>box (2)</name>
      <path>Prefabs/prefab_props/box</path>
      <position>
        <x>159.36</x>
        <y>-2.05</y>
        <z>190.8</z>
      </position>
      <rotation>
        <x>270</x>
        <y>270.000061</y>
        <z>0</z>
      </rotation>
      <scale>
        <x>1.95430791</x>
        <y>2.38557982</y>
        <z>1.954308</z>
      </scale>
      <tilePosition>
        <x>150</x>
        <y>10</y>
        <z>130</z>
      </tilePosition>
      <coordinate>
        <x>5</x>
        <y>6</y>
      </coordinate>
      <type>building</type>
    </SceneObject>
    <SceneObject>
      <name>box (3)</name>
      <path>Prefabs/prefab_props/box</path>
      <position>
        <x>154.11</x>
        <y>-3.81</y>
        <z>202.44</z>
      </position>
      <rotation>
        <x>270</x>
        <y>330.000061</y>
        <z>0</z>
      </rotation>
      <scale>
        <x>1.954308</x>
        <y>1.95430851</y>
        <z>1.954309</z>
      </scale>
      <tilePosition>
        <x>150</x>
        <y>10</y>
        <z>130</z>
      </tilePosition>
      <coordinate>
        <x>5</x>
        <y>6</y>
      </coordinate>
      <type>building</type>
    </SceneObject>
    <SceneObject>
      <name>port_wooden_bridges</name>
      <path />
      <position>
        <x>159.5</x>
        <y>-8.9</y>
        <z>160.5</z>
      </position>
      <rotation>
        <x>0</x>
        <y>0</y>
        <z>0</z>
      </rotation>
      <scale>
        <x>1</x>
        <y>1</y>
        <z>1</z>
      </scale>
      <tilePosition>
        <x>150</x>
        <y>10</y>
        <z>130</z>
      </tilePosition>
      <coordinate>
        <x>5</x>
        <y>6</y>
      </coordinate>
      <type>building</type>
    </SceneObject>
    <SceneObject>
      <name>port_wooden_bridge_b (1)</name>
      <path>Prefabs/prefab_props/port_wooden_bridge_b</path>
      <position>
        <x>202.24</x>
        <y>-9.08</y>
        <z>133.57</z>
      </position>
      <rotation>
        <x>270</x>
        <y>270</y>
        <z>0</z>
      </rotation>
      <scale>
        <x>2.246403</x>
        <y>2.246403</y>
        <z>2.246403</z>
      </scale>
      <tilePosition>
        <x>150</x>
        <y>10</y>
        <z>130</z>
      </tilePosition>
      <coordinate>
        <x>5</x>
        <y>6</y>
      </coordinate>
      <type>building</type>
    </SceneObject>
    <SceneObject>
      <name>port_wooden_bridge_a</name>
      <path>Prefabs/prefab_props/port_wooden_bridge_a</path>
      <position>
        <x>174.85</x>
        <y>-8.9</y>
        <z>160.5</z>
      </position>
      <rotation>
        <x>270</x>
        <y>180.000015</y>
        <z>0</z>
      </rotation>
      <scale>
        <x>2.24640417</x>
        <y>2.24640346</y>
        <z>2.24640346</z>
      </scale>
      <tilePosition>
        <x>150</x>
        <y>10</y>
        <z>130</z>
      </tilePosition>
      <coordinate>
        <x>5</x>
        <y>6</y>
      </coordinate>
      <type>building</type>
    </SceneObject>
    <SceneObject>
      <name>port_wooden_bridge_a (1)</name>
      <path>Prefabs/prefab_props/port_wooden_bridge_a</path>
      <position>
        <x>209.689987</x>
        <y>-8.9</y>
        <z>160.5</z>
      </position>
      <rotation>
        <x>270</x>
        <y>180.000015</y>
        <z>0</z>
      </rotation>
      <scale>
        <x>2.24640417</x>
        <y>2.24640346</y>
        <z>2.24640346</z>
      </scale>
      <tilePosition>
        <x>150</x>
        <y>10</y>
        <z>130</z>
      </tilePosition>
      <coordinate>
        <x>5</x>
        <y>6</y>
      </coordinate>
      <type>building</type>
    </SceneObject>
    <SceneObject>
      <name>port_wooden_bridge_a</name>
      <path>Prefabs/prefab_props/port_wooden_bridge_a</path>
      <position>
        <x>172.777313</x>
        <y>-8.9</y>
        <z>206.276276</z>
      </position>
      <rotation>
        <x>270</x>
        <y>148.292969</y>
        <z>0</z>
      </rotation>
      <scale>
        <x>2.67176318</x>
        <y>2.246406</y>
        <z>2.24640679</z>
      </scale>
      <tilePosition>
        <x>150</x>
        <y>10</y>
        <z>130</z>
      </tilePosition>
      <coordinate>
        <x>5</x>
        <y>6</y>
      </coordinate>
      <type>building</type>
    </SceneObject>
    <SceneObject>
      <name>port_wooden_bridge_b</name>
      <path>Prefabs/prefab_props/port_wooden_bridge_b</path>
      <position>
        <x>202.24</x>
        <y>-9.08</y>
        <z>142.99</z>
      </position>
      <rotation>
        <x>270</x>
        <y>270</y>
        <z>0</z>
      </rotation>
      <scale>
        <x>2.246403</x>
        <y>2.246403</y>
        <z>2.246403</z>
      </scale>
      <tilePosition>
        <x>150</x>
        <y>10</y>
        <z>130</z>
      </tilePosition>
      <coordinate>
        <x>5</x>
        <y>6</y>
      </coordinate>
      <type>building</type>
    </SceneObject>
    <SceneObject>
      <name>port_wooden_bridge_b_stairs</name>
      <path>Prefabs/prefab_props/port_wooden_bridge_b_stairs</path>
      <position>
        <x>202.12</x>
        <y>-9.08</y>
        <z>152.22</z>
      </position>
      <rotation>
        <x>270</x>
        <y>270.000061</y>
        <z>0</z>
      </rotation>
      <scale>
        <x>2.246402</x>
        <y>2.246402</y>
        <z>2.246402</z>
      </scale>
      <tilePosition>
        <x>150</x>
        <y>10</y>
        <z>130</z>
      </tilePosition>
      <coordinate>
        <x>5</x>
        <y>6</y>
      </coordinate>
      <type>building</type>
    </SceneObject>
    <SceneObject>
      <name>box</name>
      <path>Prefabs/prefab_props/box</path>
      <position>
        <x>158.43</x>
        <y>-3.81</y>
        <z>190.23</z>
      </position>
      <rotation>
        <x>270</x>
        <y>0</y>
        <z>0</z>
      </rotation>
      <scale>
        <x>1.95430791</x>
        <y>1.954309</y>
        <z>1.954309</z>
      </scale>
      <tilePosition>
        <x>150</x>
        <y>10</y>
        <z>130</z>
      </tilePosition>
      <coordinate>
        <x>5</x>
        <y>6</y>
      </coordinate>
      <type>building</type>
    </SceneObject>
    <SceneObject>
      <name>barrel</name>
      <path>Prefabs/prefab_props/barrel</path>
      <position>
        <x>152.42</x>
        <y>-0.76</y>
        <z>148.84</z>
      </position>
      <rotation>
        <x>270</x>
        <y>20.0000515</y>
        <z>0</z>
      </rotation>
      <scale>
        <x>1.07937086</x>
        <y>1.07937121</y>
        <z>1.07937133</z>
      </scale>
      <tilePosition>
        <x>150</x>
        <y>10</y>
        <z>130</z>
      </tilePosition>
      <coordinate>
        <x>5</x>
        <y>6</y>
      </coordinate>
      <type>building</type>
    </SceneObject>
    <SceneObject>
      <name>barrel_group (1)</name>
      <path>Prefabs/prefab_props/barrel_group</path>
      <position>
        <x>157.5</x>
        <y>-3.815</y>
        <z>147.58</z>
      </position>
      <rotation>
        <x>270</x>
        <y>20.00004</y>
        <z>0</z>
      </rotation>
      <scale>
        <x>1.291333</x>
        <y>1.29133368</y>
        <z>1.04282773</z>
      </scale>
      <tilePosition>
        <x>150</x>
        <y>10</y>
        <z>130</z>
      </tilePosition>
      <coordinate>
        <x>5</x>
        <y>6</y>
      </coordinate>
      <type>building</type>
    </SceneObject>
    <SceneObject>
      <name>barrel_group</name>
      <path>Prefabs/prefab_props/barrel_group</path>
      <position>
        <x>212.42</x>
        <y>-4</y>
        <z>159.29</z>
      </position>
      <rotation>
        <x>270</x>
        <y>20.00004</y>
        <z>0</z>
      </rotation>
      <scale>
        <x>1.02087343</x>
        <y>1.02087379</y>
        <z>0.8244156</z>
      </scale>
      <tilePosition>
        <x>150</x>
        <y>10</y>
        <z>130</z>
      </tilePosition>
      <coordinate>
        <x>5</x>
        <y>6</y>
      </coordinate>
      <type>building</type>
    </SceneObject>
    <SceneObject>
      <name>boat_01 (2)</name>
      <path>Prefabs/prefab_props/boat_01</path>
      <position>
        <x>185.5</x>
        <y>-7.1</y>
        <z>172.3</z>
      </position>
      <rotation>
        <x>270</x>
        <y>0</y>
        <z>0</z>
      </rotation>
      <scale>
        <x>1.31874955</x>
        <y>1.436474</y>
        <z>1.31875026</z>
      </scale>
      <tilePosition>
        <x>150</x>
        <y>10</y>
        <z>130</z>
      </tilePosition>
      <coordinate>
        <x>5</x>
        <y>6</y>
      </coordinate>
      <type>building</type>
    </SceneObject>
    <SceneObject>
      <name>boat_03 (2)</name>
      <path>Prefabs/prefab_props/boat_03</path>
      <position>
        <x>189.1</x>
        <y>-9.1</y>
        <z>136</z>
      </position>
      <rotation>
        <x>270</x>
        <y>79.70318</y>
        <z>0</z>
      </rotation>
      <scale>
        <x>1.70286751</x>
        <y>1.25763023</y>
        <z>1.25762987</z>
      </scale>
      <tilePosition>
        <x>150</x>
        <y>10</y>
        <z>130</z>
      </tilePosition>
      <coordinate>
        <x>5</x>
        <y>6</y>
      </coordinate>
      <type>building</type>
    </SceneObject>
    <SceneObject>
      <name>boat_01 (1)</name>
      <path>Prefabs/prefab_props/boat_01</path>
      <position>
        <x>211.780014</x>
        <y>-7.1</y>
        <z>143.69</z>
      </position>
      <rotation>
        <x>270</x>
        <y>91.78015</y>
        <z>0</z>
      </rotation>
      <scale>
        <x>1.60265911</x>
        <y>1.1948117</y>
        <z>1.1948117</z>
      </scale>
      <tilePosition>
        <x>150</x>
        <y>10</y>
        <z>130</z>
      </tilePosition>
      <coordinate>
        <x>5</x>
        <y>6</y>
      </coordinate>
      <type>building</type>
    </SceneObject>
    <SceneObject>
      <name>boat_01</name>
      <path>Prefabs/prefab_props/boat_01</path>
      <position>
        <x>189.2</x>
        <y>-7.1</y>
        <z>203</z>
      </position>
      <rotation>
        <x>270</x>
        <y>322.936737</y>
        <z>0</z>
      </rotation>
      <scale>
        <x>1.246456</x>
        <y>1.24645638</y>
        <z>1.24645638</z>
      </scale>
      <tilePosition>
        <x>150</x>
        <y>10</y>
        <z>130</z>
      </tilePosition>
      <coordinate>
        <x>5</x>
        <y>6</y>
      </coordinate>
      <type>building</type>
    </SceneObject>
    <SceneObject>
      <name>civilian_house_04</name>
      <path>Prefabs/prefab_civilian_buildings/civilian_house_04</path>
      <position>
        <x>197.354172</x>
        <y>-5.11194372</y>
        <z>186</z>
      </position>
      <rotation>
        <x>0</x>
        <y>0</y>
        <z>314.66153</z>
      </rotation>
      <scale>
        <x>1.33902216</x>
        <y>-1.3390224</y>
        <z>1.33902228</z>
      </scale>
      <tilePosition>
        <x>150</x>
        <y>10</y>
        <z>130</z>
      </tilePosition>
      <coordinate>
        <x>5</x>
        <y>6</y>
      </coordinate>
      <type>building</type>
    </SceneObject>
  </O>
</ObjectCollection>