<?xml version="1.0" encoding="Windows-1252"?>
<ObjectCollection xmlns:xsi="http://www.w3.org/2001/XMLSchema-instance" xmlns:xsd="http://www.w3.org/2001/XMLSchema">
  <O>
    <SceneObject>
      <name>cliff_06 (9)</name>
      <path>Prefabs/prefab_terrain/cliff_06</path>
      <position>
        <x>-201.3</x>
        <y>-24.6</y>
        <z>-41.5</z>
      </position>
      <rotation>
        <x>270</x>
        <y>51.2564659</y>
        <z>0</z>
      </rotation>
      <scale>
        <x>1.12535238</x>
        <y>1.64773726</y>
        <z>1</z>
      </scale>
      <tilePosition>
        <x>-250</x>
        <y>10</y>
        <z>-110</z>
      </tilePosition>
      <coordinate>
        <x>0</x>
        <y>3</y>
      </coordinate>
      <type>terrain</type>
    </SceneObject>
    <SceneObject>
      <name>cliff_02 (4)</name>
      <path>Prefabs/prefab_terrain/cliff_02</path>
      <position>
        <x>-188.3</x>
        <y>-24.4</y>
        <z>-71</z>
      </position>
      <rotation>
        <x>270</x>
        <y>65.26001</y>
        <z>0</z>
      </rotation>
      <scale>
        <x>1.29891157</x>
        <y>1.4441458</y>
        <z>1</z>
      </scale>
      <tilePosition>
        <x>-250</x>
        <y>10</y>
        <z>-110</z>
      </tilePosition>
      <coordinate>
        <x>0</x>
        <y>3</y>
      </coordinate>
      <type>terrain</type>
    </SceneObject>
    <SceneObject>
      <name>cliff_05 (4)</name>
      <path>Prefabs/prefab_terrain/cliff_05</path>
      <position>
        <x>-174</x>
        <y>-24.7</y>
        <z>-107.7</z>
      </position>
      <rotation>
        <x>270.276245</x>
        <y>173.751129</y>
        <z>270.0007</z>
      </rotation>
      <scale>
        <x>1</x>
        <y>1.046631</y>
        <z>1</z>
      </scale>
      <tilePosition>
        <x>-250</x>
        <y>10</y>
        <z>-110</z>
      </tilePosition>
      <coordinate>
        <x>0</x>
        <y>3</y>
      </coordinate>
      <type>terrain</type>
    </SceneObject>
  </O>
</ObjectCollection>